Metadata-Version: 1.1
Name: pandas-jalali
Version: 0.1.1
Summary: Manipulate with Jalali date in pandas
Home-page: https://github.com/akolpakov/pandas-jalali
Author: Andrey Kolpakov
Author-email: aakolpakov@gmail.com
License: MIT
Keywords: python pandas jalali calendar
Platform: UNKNOWN
Classifier: Development Status :: 4 - Beta
Classifier: Intended Audience :: Developers
Classifier: License :: OSI Approved :: MIT License
Classifier: Natural Language :: English
Classifier: Operating System :: Unix
Classifier: Programming Language :: Python :: 2.7
Classifier: Programming Language :: Python :: 3.3
Classifier: Programming Language :: Python :: 3.4
Classifier: Programming Language :: Python :: 3.5
Classifier: Programming Language :: Python :: Implementation :: PyPy
Classifier: Operating System :: OS Independent
